orbitmagic.cp311-win_amd64.pyd
orbitmagic-1.1.data/data/share/doc/orbitmagic/LICENSE.txt
orbitmagic-1.1.data/data/share/doc/orbitmagic/README.md
orbitmagic-1.1.dist-info/LICENSE.txt
orbitmagic-1.1.dist-info/METADATA
orbitmagic-1.1.dist-info/WHEEL
orbitmagic-1.1.dist-info/top_level.txt
orbitmagic-1.1.dist-info/RECORD
