Metadata-Version: 2.1
Name: orbitmagic
Version: 1.1
Summary: for helping magiciens
Home-page: https://github.com/JeongHan-Bae/orbitmagic
Author: JeongHan-Bae
Author-email: mastropseudo@gmail.com
License: MIT
License-File: LICENSE.txt
